{"build_webpack.md":"7a008fb9","build_front-end-engineering.md":"0e6d2aa5","build_vite.md":"68f43687","build_npm.md":"96659671","build_tool.md":"5c13322c","html_index.md":"d3cb7d09","index.md":"1c2d1472","css_index.md":"8baecf6e","javascript_js-datacommunication.md":"24cf361b","javascript_js-engine.md":"28f7fa54","javascript_index.md":"34ce803b","javascript_js-design.md":"3cf8c028","javascript_js-datatype.md":"643ca570","javascript_js-proto.md":"4f03abea","node_node-basic-module.md":"9170bd1e","typescript_ts-declare.md":"09757695","performance_build-performance.md":"cc3760b6","typescript_ts-inlay-type.md":"e92ab8e8","network_http-basics.md":"cf2371a1","network_web-construction.md":"4697fad5","network_http-cache.md":"c5ac6b4e","performance_http-performance.md":"f4c8ca92","vue_pinia.md":"c2c71807","network_web-safety.md":"f6f8025f","javascript_js-feat.md":"8544841d","javascript_js-webcomponent.md":"a6352658","react_react-basics.md":"033e3cf6","javascript_js-window.md":"a264820e","vue_vue2-reactive.md":"b5b5146f","typescript_ts-basics.md":"12e00927","vue_vue3-basic.md":"d5e4f36b"}
