{"css_css-compatibility.md":"167926cf","css_css-flex.md":"1a9e0add","css_css-special.md":"873168af","css_css-svg.md":"83548848","css_index.md":"9eae4129","html_html-form.md":"70dae9ae","html_index.md":"22474947","index.md":"3afbe928","javascript_index.md":"0488eec6","javascript_js-browser.md":"7ab2f391","javascript_js-datacommunication.md":"4766f8f2","javascript_js-datatype.md":"8f21e54e","javascript_js-design.md":"68cb5df8","javascript_js-dom.md":"67052eae","javascript_js-event.md":"a8ffbf04","javascript_js-feat.md":"bb406ea6","javascript_js-proto.md":"b469e599","javascript_js-webcomponent.md":"12409c42"}
