{"build_front-end-engineering.md":"5b6bdcc5","algorithm_structure.md":"e18b64a4","build_vite.md":"931d9333","build_build-performance.md":"c804f68d","build_http-performance.md":"07ed54aa","build_npm.md":"45bfeb6e","build_index.md":"08ac5dc8","algorithm_index.md":"eeabba6e","build_tool.md":"2b9bc52f","css_index.md":"184d8f17","frontend_react_index.md":"5c4bb1be","frontend_vue_pinia.md":"b5a0e4e5","index.md":"18cf5d42","javascript_js-datatype.md":"3cb93ada","frontend_vue_vue2-reactive.md":"31ae812d","other_ts-declare.md":"dfe53afd","frontend_react_react-hook.md":"7b6fa419","javascript_js-engine.md":"9a80f3c9","network_index.md":"75a452d1","network_web-construction.md":"cdbcaa21","network_web-nginx.md":"3953db3f","network_web-safety.md":"16de2be3","other_back-end-basic.md":"22608f02","other_front-end-basic.md":"8aca01f7","other_my.md":"048b67be","other_node-basic.md":"ff79e2b7","other_node-buffer.md":"47e6b3fa","other_node-engineering.md":"2e81fd89","other_node-progress.md":"57215969","other_node-v8.md":"fae37a10","javascript_js-webcomponent.md":"b944035e","html_index.md":"f22775a8","frontend_vue_vue3.md":"68e527b8","frontend_vue_index.md":"4232a463","other_index.md":"be2c2d19","javascript_index.md":"d521b36b","javascript_js-design.md":"0b4b1f09","other_node-basic-module.md":"18b9e7cb","other_node-async.md":"a6788c9b","javascript_js-datacommunication.md":"ef293a51","javascript_js-feat.md":"73366507","javascript_js-proto.md":"e3ce872d","network_http-cache.md":"e58d2599","other_ts-inlay-type.md":"46f484b6","javascript_js-window.md":"d8b7155c"}
