{"build_build-performance.md":"39221237","build_front-end-engineering.md":"e7598b11","algorithm_index.md":"8fd5136b","build_npm.md":"e6fd8917","build_tool.md":"59ebe7d9","build_http-performance.md":"49c2fe1b","build_index.md":"5a5cc62f","build_vite.md":"5d7f3f70","css_index.md":"2b439f26","index.md":"008a91ac","html_index.md":"0a1da633","javascript_js-proto.md":"6d6666db","javascript_js-engine.md":"f06fc79a","javascript_js-datatype.md":"a268ce60","javascript_js-feat.md":"4e24bd92","other_ts-declare.md":"aff5d329","react_index.md":"f44a5c18","network_web-construction.md":"210bc8f8","vue_vue2-reactive.md":"ed41be3f","other_node-basic-module.md":"0535cb55","other_ts-inlay-type.md":"8f799b61","vue_pinia.md":"a182655d","vue_index.md":"6f0f4fb7","react_react-hook.md":"1bef29f2","javascript_js-window.md":"51ee62d3","network_http-cache.md":"8a4b0691","network_index.md":"f1209fc1","network_web-safety.md":"b3ee203c","javascript_js-datacommunication.md":"cc71ab1e","other_index.md":"298712a2","javascript_index.md":"44a97be7","javascript_js-webcomponent.md":"0c1b166b","javascript_js-design.md":"f3bb2a81"}
